facebook_timezones/__init__.py
facebook_timezones-0.2.dist-info/LICENSE
facebook_timezones-0.2.dist-info/METADATA
facebook_timezones-0.2.dist-info/WHEEL
facebook_timezones-0.2.dist-info/top_level.txt
facebook_timezones-0.2.dist-info/RECORD
