Metadata-Version: 2.1
Name: facebook-timezones
Version: 0.2
Summary: Helpers for using timezones in the Facebook Graph API.
Home-page: https://github.com/mayple/facebook_timezones
Author: Alon Diamant
Author-email: alon@mayple.com
License: MIT
Download-URL: https://github.com/mayple/facebook_timezones/archive/0.2.tar.gz
Keywords: facebook,graph api,timezone,timezones,facebook timezones,marketing api
Platform: UNKNOWN
Classifier: Development Status :: 5 - Production/Stable
Classifier: License :: OSI Approved :: MIT License
Classifier: Natural Language :: English
Classifier: Programming Language :: Python
Classifier: Programming Language :: Python :: 3.6
Classifier: Programming Language :: Python :: 2.7
Classifier: Topic :: Internet :: WWW/HTTP :: Browsers
